Workbook

Sheet Assumptions
A1: LogiTrack Pro — สมมติฐานต้นทุน (Pricing Assumptions)
A2: ตัวเลขสีน้ำเงินคือค่าที่ปรับได้ — แก้ตรงนี้แล้วราคา/margin ทุกชีทจะคำนวณใหม่อัตโนมัติ กรอกข้อมูลต้นทุนจริงแทนค่าสมมติเมื่อพร้อม
A4: รายการ | B4: ค่า | C4: หน่วย | D4: หมายเหตุ/แหล่งที่มา
A5: ต้นทุน Infra ต่อคันต่อเดือน (Firebase: Firestore/Storage/Functions/รูปถ่าย) | B5: 60 | C5: บาท/คัน/เดือน | D5: สมมติฐาน — แทนที่ด้วยยอดบิล Firebase จริง หารด้วยจำนวนคันเฉลี่ย
A6: ต้นทุนทีม Support ต่อลูกค้าต่อเดือน (คน+เวลา) | B6: 3000 | C6: บาท/ลูกค้า/เดือน | D6: สมมติฐาน — ปรับตาม headcount และเงินเดือนทีม support จริง
A7: ขนาดกองรถเฉลี่ยต่อลูกค้า (ใช้แบ่งต้นทุน support ต่อคัน) | B7: 40 | C7: คัน | D7: สมมติฐาน
A8: เป้า Gross Margin — Model 2 (รายคัน/เดือน) | B8: 0.7 | C8: % | D8: มาตรฐาน SaaS ทั่วไป 65-80%
A9: เป้า Gross Margin — Model 1 (ขายขาด+MA) | B9: 0.55 | C9: % | D9: รวมต้นทุน deploy/implementation ครั้งแรก
A10: ต้นทุนพัฒนาสะสม (sunk cost, อ้างอิงเท่านั้น) | B10: 1800000 | C10: บาท | D10: ไม่ใช้คำนวณราคาโดยตรง — ใช้ดู payback period เท่านั้น
A11: อัตรา MA มาตรฐาน (% ของค่า License) | B11: 0.18 | C11: % | D11: อุตสาหกรรมทั่วไป 15-20%/ปี
A12: ต้นทุน Onboarding พื้นฐาน (data migration + training) | B12: 15000 | C12: บาท | D12: สมมติฐาน ต่อ 1 บริษัทลูกค้า
A15: ค่าที่คำนวณได้ (Derived)
A16: ต้นทุนรวมต่อคันต่อเดือน (infra + support ที่ปันส่วน) | B16: =$B$5+$B$6/$B$7 -> 135 | C16: บาท/คัน/เดือน
A17: ราคาขั้นต่ำที่แนะนำต่อคัน/เดือน (เพื่อให้ได้ margin เป้าหมาย Model 2) | B17: =B16/(1-$B$8) -> 450 | C17: บาท/คัน/เดือน

Sheet จุดเด่นเทียบคู่แข่ง
A1: LogiTrack Pro เทียบกับคู่แข่งในตลาด (Competitive Comparison)
A2: เทียบกับ 2 กลุ่มหลักในตลาด: (1) ผู้ให้บริการ GPS Tracking ในไทย เช่น bioWatch/GPS2GO, Forth Tracking, DRVR และ (2) Enterprise TMS ต่างประเทศ เช่น Geotab, Samsara, Oracle TMS, Blue Yonder — ข้อมูลอ้างอิงจากการสำรวจตลาดทั่วไป กรกฎาคม 2026
A4: หัวข้อเปรียบเทียบ | B4: LogiTrack Pro | C4: GPS Tracking ไทย (bioWatch / Forth / DRVR) | D4: Enterprise TMS ต่างประเทศ (Geotab / Samsara / Oracle / SAP)
A5: ระบบวางบิล/ออกใบแจ้งหนี้อัตโนมัติจาก trip | B5: มีในตัว — คำนวณจาก rate card + fuel adjustment + standby + multi-drop แล้วออก Invoice/Receipt/Excel พร้อมส่งลูกค้าได้ทันที | C5: ไม่มี — เป็นระบบติดตามตำแหน่งอย่างเดียว ต้องใช้ Excel/ระบบบัญชีแยกต่างหาก | D5: มี แต่เป็นโมดูลแยกที่ต้องซื้อเพิ่มและ implement เอง ค่าใช้จ่ายสูง
A6: ฮาร์ดแวร์ที่ต้องติดตั้งในรถ | B6: ไม่ต้อง — ทำงานผ่านแอปมือถือคนขับ ใช้ GPS ของโทรศัพท์ ลด lead time และต้นทุนติดตั้ง(ทำเพิ่ม-tracking with GPS as current) | C6: ต้องติดตั้งกล่อง GPS ตามมาตรฐาน DLT มีต้นทุนฮาร์ดแวร์+ติดตั้งต่อคัน | D6: ส่วนใหญ่ต้องมี hardware/OBD device หรือ integration เพิ่มเติม
A7: รองรับโครงสร้างเครือข่ายแบบไทย (SPX/SPK, Hub-SOC) | B7: ออกแบบเฉพาะ — แยกกลุ่มเครือข่าย Shopee(SPX) กับ J&T/SPK ตั้งแต่ระดับระยะทางถึง rate card | C7: ไม่รองรับ — เป็น tracking ทั่วไป ไม่ผูกกับ business logic ขนส่งพัสดุ | D7: ไม่มี out-of-the-box ต้อง custom development เพิ่มเองทั้งหมด
A8: Multi-drop delivery ต่อเที่ยว | B8: มีในตัว พร้อม flat extra-stop fee logic และแยกรูปหลักฐานตามจุดส่ง | C8: ไม่มี — แสดงได้แค่ตำแหน่ง ไม่มี concept ของงานส่งหลายจุดต่อเที่ยว | D8: มีในบางแพ็กเกจระดับสูง ต้องจ่ายเพิ่ม
A9: Customer self-service portal (ลูกค้าของลูกค้าดูงานเองได้) | B9: มีในตัว — customerScopeId จำกัดสิทธิ์เห็นเฉพาะข้อมูลของตัวเอง | C9: ไม่มี | D9: มีในบางแพลตฟอร์ม แต่ setup ซับซ้อนและมักมีค่าใช้จ่ายเพิ่ม
A10: รองรับหลายนิติบุคคล (multi-company) ในระบบเดียว | B10: มีในตัว — ตั้งค่า profile/ลายเซ็นแยกต่อบริษัทได้ ออกบิลแยกนิติบุคคล | C10: ไม่รองรับ ต้องแยกระบบต่อบริษัท | D10: รองรับ แต่ต้องซื้อ license แยกต่อ entity ส่วนใหญ่
A11: RBAC / Security Center ระดับองค์กร | B11: มีในตัว — capability-based role, audit log, force logout, ตรวจสอบเวอร์ชันแอปคนขับจาก admin | C11: จำกัดมาก ส่วนใหญ่มีแค่ login เดียวหรือสิทธิ์ตายตัว | D11: มีครบ แต่เป็น add-on ราคาสูงและ configuration ซับซ้อน
A12: ความเป็นเจ้าของระบบ / ผูกติด vendor | B12: เลือกได้ — โมเดลขายขาดให้ลูกค้าเป็นเจ้าของซอร์สโค้ดจริง ปรับแต่งต่อได้เอง | C12: SaaS ปิด ผูกกับ vendor ตลอดอายุการใช้งาน | D12: SaaS ปิด หรือ license ผูก vendor เช่นกัน ค่าเปลี่ยนระบบ (switching cost) สูงมาก
A13: ความเร็วในการ deploy เริ่มใช้งาน | B13: เร็ว — ไม่ต้องรอฮาร์ดแวร์ ติดตั้งแอปและ config ได้ภายในไม่กี่วัน | C13: ปานกลาง — ต้องรอคิวติดตั้งฮาร์ดแวร์ต่อคัน | D13: ช้า — โครงการ implement มักใช้เวลาหลายเดือนถึงเป็นปี
A14: รองรับภาษาไทยแบบเต็มรูปแบบ (ระบบ+เอกสาร) | B14: ใช่ — UI ไทย/อังกฤษครบ, บิลมี bahttext ภาษาไทย, หัก ณ ที่จ่ายอัตโนมัติ | C14: บางส่วน มักเน้นเฉพาะ dashboard tracking | D14: มักเป็นภาษาอังกฤษเป็นหลัก ต้อง localize เพิ่ม
A15: Vehicle maintenance & ค่าใช้จ่ายรถ (PM/CM) | B15: มีในตัว รวมกับข้อมูลกองรถและต้นทุนต่อคันในระบบเดียว | C15: ไม่มี | D15: มีในบางแพ็กเกจระดับ enterprise เท่านั้น
A18: สรุป:
A19: • เทียบกับ GPS Tracking ไทย: เราไม่ใช่แค่ tracking แต่เป็นระบบปฏิบัติการ+บัญชีครบวงจร ไม่ต้องใช้ฮาร์ดแวร์ deploy ไว กว่ามาก
A20: • เทียบกับ Enterprise TMS ต่างประเทศ: เราถูกกว่ามาก, deploy เร็วกว่ามาก, และมี business logic เฉพาะตลาดไทย/เครือข่ายพัสดุที่ระบบต่างประเทศไม่มีให้ off-the-shelf
A21: • จุดต่างที่ชัดที่สุด: โมเดลขายขาดให้ลูกค้าเป็นเจ้าของระบบได้จริง — แทบไม่มีคู่แข่งรายใดในตลาดเสนอทางเลือกนี้
A22: • ข้อมูลคู่แข่งเป็นภาพรวมจากตลาดทั่วไป ควรอัปเดตเมื่อมีข้อมูลราคา/ฟีเจอร์ล่าสุดของคู่แข่งแต่ละรายจริง

Sheet Model 1 - ขายขาด+MA
A1: โมเดล 1: ขายขาด (One-time License) + ค่า MA รายปี
A2: MA ปีที่ 1 รวมอยู่ในค่า License แล้ว (ฟรี) — เริ่มเก็บค่า MA ตั้งแต่ปีที่ 2 เป็นต้นไป ตามอัตรา % ที่ตั้งไว้ต่อ tier
A4: Tier | B4: ขนาดกองรถ (คัน) | C4: จำนวนบริษัท (multi-tenant) | D4: ค่า License (ครั้งเดียว) | E4: อัตรา MA/ปี (%) | F4: ค่า MA/ปี (บาท) | G4: รวม 3 ปี (License + MA ปี2-3) | H4: รายละเอียดที่รวมอยู่
A5: Starter | B5: 1 – 30 | C5: 1 บริษัท | D5: 590000 | E5: 0.18 | F5: =D5*E5 -> 106200 | G5: =D5+F5*2 -> 802400 | H5: Core TMS (mobile driver app + web admin), first-mile/line-haul, driver monitor, fuel & vehicle expense, basic maintenance log, RBAC พื้นฐาน, deploy on ลูกค้า/Firebase project เดียว
A6: Growth | B6: 31 – 100 | C6: 1 บริษัท (เพิ่ม multi-company ได้เป็น add-on) | D6: 1290000 | E6: 0.18 | F6: =D6*E6 -> 232200 | G6: =D6+F6*2 -> 1754400 | H6: ทุกอย่างใน Starter + Billing/Rate Card engine, multi-drop & standby billing, hub-SOC distance matrix, security center, audit log, CI/CD deploy pipeline
A7: Enterprise | B7: 101 – 300 | C7: สูงสุด 3 บริษัทในกลุ่ม | D7: 2490000 | E7: 0.16 | F7: =D7*E7 -> 398400 | G7: =D7+F7*2 -> 3286800 | H7: ทุกอย่างใน Growth + customer portal (customerScopeId), company profile หลายบริษัท, priority onboarding, custom rate card template, dedicated Firebase project
A8: Enterprise+ / Group | B8: 300+ | C8: unlimited (ตามตกลง) | D8: ขอใบเสนอราคา (Quote) | E8: 0.15 | F8: - | G8: - | H8: Custom scope — ใบเสนอราคาแยกตามจำนวนบริษัท/กองรถ/ฟีเจอร์เสริม (white-label, on-prem option, SLA พิเศษ)
A11: หมายเหตุ:
A12: • ค่า License รวม: ติดตั้งระบบ (mobile + web), data migration เบื้องต้น, training ทีมงาน 1 รอบ, MA ปีที่ 1 ฟรี
A13: • MA ครอบคลุม: bug fix, security patch, minor feature update, support ตามเวลาทำการ (ไม่รวม feature ใหม่ขนาดใหญ่)
A14: • Custom feature/integration นอกสโคป คิดแยกเป็นโปรเจกต์เพิ่มเติม (ดูชีท Add-ons)
A15: • เหมาะกับลูกค้าที่ต้องการเป็นเจ้าของระบบ (on-prem/dedicated) และมี budget capex ชัดเจน

Sheet Model 2 - รายคันต่อเดือน
A1: โมเดล 2: ค่าบริการรายคันต่อเดือน (Per-Vehicle Subscription / SaaS)
A2: รวม hosting, การอัปเดตระบบ, และ support ไว้ในราคาแล้ว — ไม่มีค่า License แยก | จ่ายรายปีล่วงหน้ารับส่วนลด 2 เดือน (~16.7%)
A4: Tier | B4: ช่วงจำนวนคัน | C4: ราคา/คัน/เดือน (บาท) | D4: ค่า Setup ครั้งเดียว | E4: ตัวอย่างรายได้/เดือน (กึ่งกลางช่วง) | F4: ต้นทุน/เดือน (อ้างอิง Assumptions) | G4: Gross Margin ที่ได้จริง | H4: ราคาขั้นต่ำที่แนะนำ | I4: ผ่านเกณฑ์ margin เป้าหมาย?
A5: Tier 1 — Starter | B5: 1 – 20 | C5: 990 | D5: 25000 | E5: =C5*10.5 -> 10395 | F5: =Assumptions!$B$16*10.5 -> 1417.5 | G5: =(E5-F5)/E5 -> 0.86363636 | H5: =Assumptions!$B$17 -> 450 | I5: =IF(C5>=H5,"ผ่าน","ต่ำกว่าเป้า") -> ผ่าน
A6: Tier 2 — Growth | B6: 21 – 100 | C6: 790 | D6: 60000 | E6: =C6*60.5 -> 47795 | F6: =Assumptions!$B$16*60.5 -> 8167.5 | G6: =(E6-F6)/E6 -> 0.82911392 | H6: =Assumptions!$B$17 -> 450 | I6: =IF(C6>=H6,"ผ่าน","ต่ำกว่าเป้า") -> ผ่าน
A7: Tier 3 — Scale | B7: 101 – 300 | C7: 590 | D7: 120000 | E7: =C7*200.5 -> 118295 | F7: =Assumptions!$B$16*200.5 -> 27067.5 | G7: =(E7-F7)/E7 -> 0.77118644 | H7: =Assumptions!$B$17 -> 450 | I7: =IF(C7>=H7,"ผ่าน","ต่ำกว่าเป้า") -> ผ่าน
A8: Tier 4 — Enterprise | B8: 301+ (custom) | C8: เจรจาต่อรอง (~450 เป็นจุดอ้างอิง) | D8: เจรจาต่อรอง | E8: - | F8: - | G8: - | H8: - | I8: -
A11: หมายเหตุ:
A12: • ราคาต่อคันเป็นแบบ tiered (ไม่ใช่ blended) — ลูกค้าจ่ายตามอัตรา tier ที่กองรถของตัวเองอยู่ ไม่ใช่ขั้นบันไดสะสม
A13: • ค่า Setup ครอบคลุม: data migration, ตั้งค่า hub/rate card เริ่มต้น, training ทีมงาน 1 รอบ
A14: • สัญญาขั้นต่ำแนะนำ 12 เดือน; ยกเลิกก่อนกำหนดคิดค่า setup คืนตามสัดส่วน
A15: • เหมาะกับลูกค้าที่ต้องการ opex ล้วน ไม่มี capex ก้อนใหญ่ และต้องการให้ผู้พัฒนาดูแล hosting/อัปเดตให้ตลอด

Sheet Add-ons เสริม
A1: บริการเสริม / Add-ons (ใช้ได้ทั้ง 2 โมเดล)
A3: บริการเสริม | B3: ราคา | C3: หน่วย | D3: หมายเหตุ
A4: บริษัทเพิ่มเติม (multi-company / companyScope) | B4: 15000 | C4: บาท/บริษัท/ปี | D4: สำหรับกลุ่มธุรกิจที่มีหลายนิติบุคคลออกบิลแยกกัน
A5: Priority Support SLA (ตอบกลับ <2 ชม., 24/7) | B5: 8000 | C5: บาท/เดือน | D5: จากมาตรฐาน 1 วันทำการ
A6: ตั้งค่า Rate Card / Hub-SOC เพิ่มเติมนอกสโคป | B6: 3000 | C6: บาท/ชั่วโมง | D6: อัตรา implementation consultant
A7: Training เพิ่มเติม (on-site) | B7: 12000 | C7: บาท/วัน | D7: ไม่รวมค่าเดินทาง
A8: White-label branding (โลโก้/สี/โดเมนลูกค้า) | B8: 80000 | C8: บาท ครั้งเดียว | D8: เฉพาะ Model 1 Enterprise+ ขึ้นไป
A9: Data migration จากระบบเดิม (นอกเหนือ setup พื้นฐาน) | B9: 25000 | C9: บาท/โปรเจกต์ | D9: ประเมินตามความซับซ้อนข้อมูลจริง
A10: พื้นที่เก็บรูปภาพ/เอกสารเพิ่ม (เกิน quota มาตรฐาน) | B10: 500 | C10: บาท/10GB/เดือน | D10: pass-through ต้นทุน Firebase Storage
A11: SMS/แจ้งเตือนนอกระบบ (ถ้ามีการเชื่อมต่อ) | B11: ตามต้นทุนจริง +15% | C11: บาท/ข้อความ | D11: pass-through cost บวก margin
A12: Custom feature / integration พิเศษ | B12: ขอใบเสนอราคา | C12: - | D12: ประเมินเป็นโปรเจกต์แยก (man-day based)

Sheet เปรียบเทียบ 3 ปี
A1: เปรียบเทียบต้นทุนรวม 3 ปี (TCO) — Model 1 vs Model 2
A2: ตัวเลขดึงจากราคาที่ตั้งไว้ในชีท Model 1 และ Model 2 โดยอัตโนมัติ — ปรับราคา tier แล้วตารางนี้จะอัปเดตเอง
A4: ขนาดกองรถตัวอย่าง (คัน) | B4: Model 1: License + MA (2 ปีถัดไป) รวม 3 ปี | C4: Model 2: รายคัน x 36 เดือน + Setup รวม 3 ปี | D4: ส่วนต่าง | E4: โมเดลที่ถูกกว่าใน 3 ปี | F4: ข้อเสนอแนะ
A5: 20 คัน (Starter) | B5: ='Model 1 - ขายขาด+MA'!G5 -> 802400 | C5: ='Model 2 - รายคันต่อเดือน'!C5*20*36+'Model 2 - รายคันต่อเดือน'!D5 -> 737800 | D5: =B5-C5 -> 64600 | E5: =IF(B5<C5,"Model 1 ถูกกว่า",IF(B5>C5,"Model 2 ถูกกว่า","เท่ากัน")) -> Model 2 ถูกกว่า | F5: เลือกตาม cash flow: Model 1 ถ้ามี capex, Model 2 ถ้าต้องการ opex ล้วน
A6: 60 คัน (Growth) | B6: ='Model 1 - ขายขาด+MA'!G6 -> 1754400 | C6: ='Model 2 - รายคันต่อเดือน'!C6*60*36+'Model 2 - รายคันต่อเดือน'!D6 -> 1766400 | D6: =B6-C6 -> -12000 | E6: =IF(B6<C6,"Model 1 ถูกกว่า",IF(B6>C6,"Model 2 ถูกกว่า","เท่ากัน")) -> Model 1 ถูกกว่า | F6: เลือกตาม cash flow: Model 1 ถ้ามี capex, Model 2 ถ้าต้องการ opex ล้วน
A7: 150 คัน (Scale/Enterprise) | B7: ='Model 1 - ขายขาด+MA'!G7 -> 3286800 | C7: ='Model 2 - รายคันต่อเดือน'!C7*150*36+'Model 2 - รายคันต่อเดือน'!D7 -> 3306000 | D7: =B7-C7 -> -19200 | E7: =IF(B7<C7,"Model 1 ถูกกว่า",IF(B7>C7,"Model 2 ถูกกว่า","เท่ากัน")) -> Model 1 ถูกกว่า | F7: เลือกตาม cash flow: Model 1 ถ้ามี capex, Model 2 ถ้าต้องการ opex ล้วน
A10: สรุปการเลือกใช้โมเดล:
A11: • Model 1 (ขายขาด+MA) เหมาะกับ: ลูกค้าองค์กร/3PL ที่มีงบ capex ชัดเจน ต้องการ 'เป็นเจ้าของระบบ', ต้องการ data residency/dedicated infra, มองเป็นสินทรัพย์ระยะยาว
A12: • Model 2 (รายคัน/เดือน) เหมาะกับ: ลูกค้า SME ที่กองรถยังไม่นิ่ง (ขยาย/หดตัวได้), ต้องการเริ่มต้นต้นทุนต่ำ, ไม่อยากดูแล infra เอง, ทดลองระบบก่อนตัดสินใจระยะยาว
A13: • ทั้งสองโมเดลถูกออกแบบให้ TCO 3 ปีใกล้เคียงกันในแต่ละ tier (ดูตารางด้านบน) — ความต่างหลักคือจังหวะกระแสเงินสด ไม่ใช่ราคารวม
A14: • แนะนำให้เสนอทั้ง 2 โมเดลคู่กันเสมอ แล้วให้ลูกค้าเลือกตามนโยบายการเงินของบริษัทตัวเอง
